SEACells/__init__.py
SEACells/accessibility.py
SEACells/build_graph.py
SEACells/core.py
SEACells/domainadapt.py
SEACells/evaluate.py
SEACells/genescores.py
SEACells/plot.py
SEACells/preprocess.py
SEACells/utils.py
SEACells/version.py
SEACells-0.3.2.dist-info/LICENSE.txt
SEACells-0.3.2.dist-info/METADATA
SEACells-0.3.2.dist-info/WHEEL
SEACells-0.3.2.dist-info/top_level.txt
SEACells-0.3.2.dist-info/RECORD
