Metadata-Version: 2.1
Name: SEACells
Version: 0.3.2
Summary: 
Home-page: https://github.com/dpeerlab/SEACells
Author: Pe'er Lab
Author-email: scp2152@columbia.edu
Classifier: Programming Language :: Python :: 3
Classifier: License :: OSI Approved :: MIT License
Classifier: Operating System :: OS Independent
Requires-Python: >=3.8.0
License-File: LICENSE.txt
Requires-Dist: numpy
Requires-Dist: pandas
Requires-Dist: palantir
Requires-Dist: scanpy (>1.8)
Requires-Dist: anndata
Requires-Dist: numba (>=0.51.2)
Requires-Dist: scipy (>=1.5)
Requires-Dist: pyranges
